docs/source/conf.py
examples/example_scripts/detector_Caffe_SSDMobileNet.py
examples/example_scripts/detector_TF_SSDMobileNetV2.py
examples/example_scripts/detector_YOLOv3.py
examples/example_scripts/mot_Caffe_SSDMobileNet.py
examples/example_scripts/mot_TF_SSDMobileNet.py
examples/example_scripts/mot_YOLOv3.py
examples/motmetrics_eval/motmeterics.py
motrackers/__init__.py
motrackers/centroid_kf_tracker.py
motrackers/iou_tracker.py
motrackers/kalman_tracker.py
motrackers/sort_tracker.py
motrackers/track.py
motrackers/tracker.py
motrackers/tracker_img.py
motrackers/detectors/__init__.py
motrackers/detectors/caffe.py
motrackers/detectors/detector.py
motrackers/detectors/tf.py
motrackers/detectors/yolo.py
motrackers/utils/__init__.py
motrackers/utils/filechooser_utils.py
motrackers/utils/misc.py
motrackers-0.0.2.dist-info/LICENSE
motrackers-0.0.2.dist-info/METADATA
motrackers-0.0.2.dist-info/WHEEL
motrackers-0.0.2.dist-info/top_level.txt
motrackers-0.0.2.dist-info/RECORD
