Metadata-Version: 2.1
Name: motrackers
Version: 0.0.2
Summary: Multi-object trackers in Python
Author-email: "Aditya M. Deshpande" <adityadeshpande2010@gmail.com>
Project-URL: homepath, https://adipandas.github.io/multi-object-tracker
Project-URL: repository, https://github.com/adipandas/multi-object-tracker
Keywords: tracking,object,multi-object,python
Classifier: Programming Language :: Python :: 3
Requires-Python: >3.6
License-File: LICENSE
Requires-Dist: numpy
Requires-Dist: scipy
Requires-Dist: matplotlib
Requires-Dist: opencv-python
Requires-Dist: pandas
Requires-Dist: motmetrics
Requires-Dist: setuptools
Requires-Dist: ipyfilechooser
Provides-Extra: docs
Requires-Dist: sphinx ; extra == 'docs'
Requires-Dist: m2r2 ; extra == 'docs'
